tabledata/__init__.py
tabledata/__version__.py
tabledata/_common.py
tabledata/_constant.py
tabledata/_converter.py
tabledata/_core.py
tabledata/error.py
tabledata/normalizer.py
tabledata/py.typed
tabledata/_logger/__init__.py
tabledata/_logger/_logger.py
tabledata/_logger/_null_logger.py
tabledata-1.3.3.dist-info/LICENSE
tabledata-1.3.3.dist-info/METADATA
tabledata-1.3.3.dist-info/WHEEL
tabledata-1.3.3.dist-info/top_level.txt
tabledata-1.3.3.dist-info/RECORD
