Metadata-Version: 2.1
Name: tabledata
Version: 1.3.3
Summary: tabledata is a Python library to represent tabular data. Used for pytablewriter/pytablereader/SimpleSQLite/etc.
Home-page: https://github.com/thombashi/tabledata
Author: Tsuyoshi Hombashi
Author-email: tsuyoshi.hombashi@gmail.com
License: MIT License
Project-URL: Changlog, https://github.com/thombashi/tabledata/releases
Project-URL: Documentation, https://tabledata.rtfd.io/
Project-URL: Source, https://github.com/thombashi/tabledata
Project-URL: Tracker, https://github.com/thombashi/tabledata/issues
Keywords: table
Classifier: Development Status :: 5 - Production/Stable
Classifier: Intended Audience :: Developers
Classifier: Intended Audience :: Information Technology
Classifier: License :: OSI Approved :: MIT License
Classifier: Operating System :: OS Independent
Classifier: Programming Language :: Python :: 3
Classifier: Programming Language :: Python :: 3.7
Classifier: Programming Language :: Python :: 3.8
Classifier: Programming Language :: Python :: 3.9
Classifier: Programming Language :: Python :: 3.10
Classifier: Programming Language :: Python :: 3.11
Classifier: Programming Language :: Python :: 3 :: Only
Classifier: Programming Language :: Python :: Implementation :: CPython
Classifier: Programming Language :: Python :: Implementation :: PyPy
Classifier: Topic :: Software Development :: Libraries
Classifier: Topic :: Software Development :: Libraries :: Python Modules
Requires-Python: >=3.7
License-File: LICENSE
Requires-Dist: DataProperty<2,>=1.0.1
Requires-Dist: typepy<2,>=1.2.0
Provides-Extra: logging
Requires-Dist: loguru<1,>=0.4.1; extra == "logging"
Provides-Extra: test
Requires-Dist: pytablewriter>=0.46; extra == "test"
Requires-Dist: pytest; extra == "test"
